{
  "port": "BaseLibraries-Main",
  "name": "Gmp",
  "version": "6.3.0",
  "architectures": ["x86_64"],
  "description": "GMP library for arbitrary precision arithmetic, operating on signed integers, rational numbers, and floating-point numbers",
  "website": "https://www.gnu.org/software/gmp/",
  "installedFiles": [],
  "dependencies": [
    {
      "port": "SystemBase-Main",
      "name": "SystemBase",
      "version": ">=0.2.0",
      "options": ["Pass2"]
    }
  ],
  "kernelDependencies": [],
  "options": [
    {
      "name": "32Bits",
      "description": "Enable 32 bits support",
      "active": false,
      "dependencies": [],
      "kernelDependencies": ["CONFIG_IA32_EMULATION"]
    },
    {
      "name": "x32Bits",
      "description": "Enable x32 bits support",
      "active": false,
      "dependencies": [],
      "kernelDependencies": ["CONFIG_X86_X32"]
    }
  ],
  "uniqueDependencies": [],
  "uniqueOptions": [],
  "selectedDependencies": [],
  "allowCodependencies": []
}
