{
  "port": "BaseLibraries-Main",
  "name": "Libxslt",
  "version": "1.1.38",
  "architectures": [
    "x86_64"
  ],
  "description": "XSLT processor based on libxml2",
  "website": "https://gitlab.gnome.org/GNOME/libxslt",
  "installedFiles": [],
  "dependencies": [
    {
      "name": "Libxml2",
      "version": "2.10.4",
      "options": []
    }
  ],
  "kernelDependencies": [],
  "options": [
    {
      "name": "Docbook-Xml",
      "description": "Enable docbook-xml support",
      "active": false,
      "dependencies": [
        {
          "name": "Docbook-Xml",
          "version": "4.5.0",
          "options": []
        }
      ],
      "kernelDependencies": []
    },
    {
      "name": "Docbook-Xsl-Nons",
      "description": "Enable docbook-xsl-nons support",
      "active": false,
      "dependencies": [
        {
          "name": "Docbook-Xsl-Nons",
          "version": "1.79.2",
          "options": []
        }
      ],
      "kernelDependencies": []
    }
  ],
  "uniqueOptions": []
}
